{
  "project_info": {
    "project_number": "686535885370",
    "project_id": "quik-genz-erp",
    "storage_bucket": "quik-genz-erp.firebasestorage.app"
  },
  "client": [
    {
      "client_info": {
        "mobilesdk_app_id": "1:686535885370:android:86014c30c21b4f6bd42b03",
        "android_client_info": {
          "package_name": "com.example.genz_protech"
        }
      },
      "oauth_client": [],
      "api_key": [
        {
          "current_key": "AIzaSyBFHrlI_0I4GpPA_BAU4JeMjhoosjVNuKs"
        }
      ],
      "services": {
        "appinvite_service": {
          "other_platform_oauth_client": []
        }
      }
    }
  ],
  "configuration_version": "1"
}